README.rst
setup.py
src/aliyun_oss_python_sdk_managed_credentials_provider.egg-info/PKG-INFO
src/aliyun_oss_python_sdk_managed_credentials_provider.egg-info/SOURCES.txt
src/aliyun_oss_python_sdk_managed_credentials_provider.egg-info/dependency_links.txt
src/aliyun_oss_python_sdk_managed_credentials_provider.egg-info/requires.txt
src/aliyun_oss_python_sdk_managed_credentials_provider.egg-info/top_level.txt
src/aliyun_sdk_secretsmanager_oss_plugin/__init__.py
src/aliyun_sdk_secretsmanager_oss_plugin/oss_ak_expire_handler.py
src/aliyun_sdk_secretsmanager_oss_plugin/proxy_bucket.py
src/aliyun_sdk_secretsmanager_oss_plugin/secretsmanager_oss_plugin_credential_updater.py
src/aliyun_sdk_secretsmanager_oss_plugin/secretsmanager_oss_plugin_manager.py
src/aliyun_sdk_secretsmanager_oss_plugin/secretsmanger_plugin_auth.py